mcp_postgres_duwenji/__init__.py
mcp_postgres_duwenji/assets/postgresql.conf
mcp_postgres_duwenji/config.py
mcp_postgres_duwenji/context.py
mcp_postgres_duwenji/database.py
mcp_postgres_duwenji/docker_manager.py
mcp_postgres_duwenji/main.py
mcp_postgres_duwenji/prompts.py
mcp_postgres_duwenji/protocol_logging.py
mcp_postgres_duwenji/resources.py
mcp_postgres_duwenji/shared.py
mcp_postgres_duwenji/tools/__init__.py
mcp_postgres_duwenji/tools/crud_tools.py
mcp_postgres_duwenji/tools/elicitation_tools.py
mcp_postgres_duwenji/tools/sampling_integration.py
mcp_postgres_duwenji/tools/sampling_tools.py
mcp_postgres_duwenji/tools/schema_tools.py
mcp_postgres_duwenji/tools/table_tools.py
mcp_postgres_duwenji/tools/transaction_tools.py
mcp_postgres_duwenji-1.2.54.dist-info/WHEEL
mcp_postgres_duwenji-1.2.54.dist-info/entry_points.txt
mcp_postgres_duwenji-1.2.54.dist-info/METADATA
mcp_postgres_duwenji-1.2.54.dist-info/RECORD
