Metadata-Version: 2.3
Name: mcp-postgres-duwenji
Version: 1.2.54
Summary: MCP server for PostgreSQL database operations
Keywords: mcp,PostgreSQL
Author: mcp-postgres, duwenji
Author-email: duwenji <duwenji@gmail.com>
License: MIT License
Classifier: Development Status :: 4 - Beta
Classifier: License :: OSI Approved :: MIT License
Classifier: Programming Language :: Python
Classifier: Programming Language :: Python :: 3.10
Classifier: Programming Language :: Python :: 3.11
Classifier: Programming Language :: Python :: 3.12
Classifier: Programming Language :: Python :: 3.13
Requires-Dist: build>=1.3.0
Requires-Dist: mcp>=1.0.0
Requires-Dist: psycopg2-binary>=2.9.0
Requires-Dist: pydantic>=2.0.0
Requires-Dist: python-dotenv>=1.0.0
Requires-Dist: twine>=6.2.0
Requires-Dist: docker>=6.0.0
Requires-Dist: types-docker>=7.1.0.20251009
Requires-Dist: pytest>=8.4.2 ; extra == 'dev'
Requires-Dist: pytest-asyncio>=0.21.0 ; extra == 'dev'
Requires-Dist: pytest-cov>=7.0.0 ; extra == 'dev'
Requires-Dist: pytest-mock>=3.0.0 ; extra == 'dev'
Requires-Dist: pytest-xdist>=3.0.0 ; extra == 'dev'
Requires-Dist: black>=23.0.0 ; extra == 'dev'
Requires-Dist: flake8>=6.0.0 ; extra == 'dev'
Requires-Dist: mypy>=1.0.0 ; extra == 'dev'
Requires-Dist: freezegun>=1.0.0 ; extra == 'dev'
Requires-Dist: bandit>=1.7.0 ; extra == 'dev'
Requires-Python: >=3.10
Provides-Extra: dev
